currency/__init__.py
xl3335currency-0.1.3.dist-info/METADATA
xl3335currency-0.1.3.dist-info/WHEEL
xl3335currency-0.1.3.dist-info/top_level.txt
xl3335currency-0.1.3.dist-info/RECORD
