Metadata-Version: 2.1
Name: xl3335currency
Version: 0.1.3
Summary: This package is for concurrency calculation
Home-page: https://currency-xwl.readthedocs.io/
Author: Xiuwen Li
Author-email: xl3335@nyu.edu
License: MIT
Platform: UNKNOWN
Classifier: Intended Audience :: Developers
Classifier: License :: OSI Approved :: MIT License
Classifier: Programming Language :: Python
Classifier: Programming Language :: Python :: 3
Classifier: Programming Language :: Python :: 3.6
Classifier: Programming Language :: Python :: 3.7
Classifier: Programming Language :: Python :: 3.8
Classifier: Programming Language :: Python :: 3.9
Classifier: Operating System :: OS Independent
